astroalign.py
astroalign-2.6.2.dist-info/METADATA
astroalign-2.6.2.dist-info/WHEEL
astroalign-2.6.2.dist-info/top_level.txt
astroalign-2.6.2.dist-info/RECORD
