Metadata-Version: 2.4
Name: astroalign
Version: 2.6.2
Summary: Astrometric Alignment of Images
Author-email: Martin Beroiz <martinberoiz@gmail.com>
Maintainer-email: Martin Beroiz <martinberoiz@gmail.com>
License: MIT License
Project-URL: homepage, https://astroalign.quatrope.org
Project-URL: documentation, https://astroalign.readthedocs.io/
Project-URL: source, https://github.com/quatrope/astroalign
Keywords: astronomy,registration,alignment,asterism-matching,stellar-astronomical-images
Requires-Python: >=3.10
Requires-Dist: numpy
Requires-Dist: scipy
Requires-Dist: scikit-image
Requires-Dist: sep>=1.4.0
